setup.py
_cffi_builder/cbuffer_builder.py
cobjects/__init__.py
cobjects/cbuffer.py
cobjects/cfield.py
cobjects/cobject.py
cobjects.egg-info/PKG-INFO
cobjects.egg-info/SOURCES.txt
cobjects.egg-info/dependency_links.txt
cobjects.egg-info/requires.txt
cobjects.egg-info/top_level.txt
src/cbuffer.c
src/cbuffer.h