Metadata-Version: 1.2
Name: cobjects
Version: 0.0.9
Summary: Manage C data from Python for C libraries
Home-page: https://github.com/rdemaria/cobjects
Author: Riccardo De Maria
Author-email: riccardo.de.maria@cern.ch
License: UNKNOWN
Platform: UNKNOWN
Requires-Python: >=3.6
